mpcforces_extractor/__init__.py
mpcforces_extractor/api/config.py
mpcforces_extractor/api/db/__init__.py
mpcforces_extractor/api/db/database.py
mpcforces_extractor/api/db/models.py
mpcforces_extractor/api/db/schemas.py
mpcforces_extractor/api/db/test_database.py
mpcforces_extractor/api/dependencies.py
mpcforces_extractor/api/main.py
mpcforces_extractor/api/routes/database.py
mpcforces_extractor/api/routes/extractor.py
mpcforces_extractor/api/routes/file_upload.py
mpcforces_extractor/api/routes/html_routes.py
mpcforces_extractor/api/routes/nodes.py
mpcforces_extractor/api/routes/rbe2s.py
mpcforces_extractor/api/routes/rbe3s.py
mpcforces_extractor/api/routes/subcases.py
mpcforces_extractor/api/test_main.py
mpcforces_extractor/app.py
mpcforces_extractor/datastructure/__init__.py
mpcforces_extractor/datastructure/entities.py
mpcforces_extractor/datastructure/loads.py
mpcforces_extractor/datastructure/rigids.py
mpcforces_extractor/datastructure/subcases.py
mpcforces_extractor/datastructure/test_entities.py
mpcforces_extractor/datastructure/test_rigids.py
mpcforces_extractor/force_extractor.py
mpcforces_extractor/frontend/static/assets/favicon.ico
mpcforces_extractor/frontend/static/assets/github.svg
mpcforces_extractor/frontend/static/css/styles.css
mpcforces_extractor/frontend/static/js/common.js
mpcforces_extractor/frontend/static/js/mainPage.js
mpcforces_extractor/frontend/static/js/mpcPage.js
mpcforces_extractor/frontend/static/js/nodePage.js
mpcforces_extractor/frontend/templates/main.html
mpcforces_extractor/frontend/templates/mpcs.html
mpcforces_extractor/frontend/templates/navbar.html
mpcforces_extractor/frontend/templates/nodes.html
mpcforces_extractor/main.py
mpcforces_extractor/reader/__init__.py
mpcforces_extractor/reader/modelreaders.py
mpcforces_extractor/reader/mpcforces_reader.py
mpcforces_extractor/reader/test_modelreaders.py
mpcforces_extractor/reader/test_mpcforces_reader.py
mpcforces_extractor/test_force_extractor.py
mpcforces_extractor-0.1.7.4.dist-info/LICENSE
mpcforces_extractor-0.1.7.4.dist-info/METADATA
mpcforces_extractor-0.1.7.4.dist-info/WHEEL
mpcforces_extractor-0.1.7.4.dist-info/entry_points.txt
mpcforces_extractor-0.1.7.4.dist-info/RECORD
