Metadata-Version: 2.1
Name: mpcforces-extractor
Version: 0.1.7.4
Summary: A simple toolbox for getting mpc forces from output files from Optistruct
License: MIT
Author: Manuel
Author-email: manuel.ramsaier89@gmail.com
Requires-Python: >=3.10,<4.0
Classifier: License :: OSI Approved :: MIT License
Classifier: Programming Language :: Python :: 3
Classifier: Programming Language :: Python :: 3.10
Classifier: Programming Language :: Python :: 3.11
Classifier: Programming Language :: Python :: 3.12
Requires-Dist: fastapi (>=0.115.0,<0.116.0)
Requires-Dist: jinja2 (>=3.1.4,<4.0.0)
Requires-Dist: networkx (>=3.3,<4.0)
Requires-Dist: python-multipart (>=0.0.12,<0.0.13)
Requires-Dist: sqlmodel (>=0.0.22,<0.0.23)
Requires-Dist: typer (>=0.12.5,<0.13.0)
Requires-Dist: uvicorn[standard] (>=0.31.1,<0.32.0)
